{
  "schema_version": "1.0",
  "file_info": {
    "filename": "66673489-a62e-4f57-b149-9247bb680274_test_suspicious.exe",
    "filepath": "C:\\Users\\Piyush\\Desktop\\stealthOS\\backend\\uploads\\66673489-a62e-4f57-b149-9247bb680274_test_suspicious.exe",
    "file_size_bytes": 161362,
    "file_size_kb": 157.58,
    "modified_time": "2026-07-08T18:48:03.340113",
    "analysis_timestamp": "2026-07-08T18:48:03.838464",
    "md5": "ed6126ce7be813f88a094af99591cee1",
    "sha1": "31a7149fd05a90aadc0d538cf621ca6c9b380e0f",
    "sha256": "38cd71a5b5624306f8e7bac07e249eb99758eee8231bb4f17926dd6ead8bb854"
  },
  "file_type": {
    "extension": ".exe",
    "mime_type": "application/x-dosexec",
    "description": "PE32 executable (console) Intel 80386, for MS Windows",
    "is_executable": true,
    "is_archive": false
  },
  "pe_analysis": {
    "is_valid_pe": true,
    "machine_type": "IMAGE_FILE_MACHINE_I386",
    "timestamp": 1782751255,
    "entry_point": "0x12e0",
    "image_base": "0x400000",
    "subsystem": "IMAGE_SUBSYSTEM_WINDOWS_CUI",
    "dll_characteristics": [],
    "sections": [
      {
        "name": ".text",
        "virtual_address": "0x1000",
        "virtual_size": 11364,
        "raw_size": 11776,
        "entropy": 6.0606,
        "characteristics": "0x60500060",
        "is_executable": true,
        "is_writable": false,
        "is_readable": true
      },
      {
        "name": ".data",
        "virtual_address": "0x4000",
        "virtual_size": 28,
        "raw_size": 512,
        "entropy": 0.2224,
        "characteristics": "0xc0300040",
        "is_executable": false,
        "is_writable": true,
        "is_readable": true
      },
      {
        "name": ".rdata",
        "virtual_address": "0x5000",
        "virtual_size": 884,
        "raw_size": 1024,
        "entropy": 4.648,
        "characteristics": "0x40300040",
        "is_executable": false,
        "is_writable": false,
        "is_readable": true
      },
      {
        "name": "/4",
        "virtual_address": "0x6000",
        "virtual_size": 2480,
        "raw_size": 2560,
        "entropy": 4.7534,
        "characteristics": "0x40300040",
        "is_executable": false,
        "is_writable": false,
        "is_readable": true
      },
      {
        "name": ".bss",
        "virtual_address": "0x7000",
        "virtual_size": 112,
        "raw_size": 0,
        "entropy": 0.0,
        "characteristics": "0xc0300080",
        "is_executable": false,
        "is_writable": true,
        "is_readable": true
      },
      {
        "name": ".idata",
        "virtual_address": "0x8000",
        "virtual_size": 1488,
        "raw_size": 1536,
        "entropy": 4.5745,
        "characteristics": "0xc0300040",
        "is_executable": false,
        "is_writable": true,
        "is_readable": true
      },
      {
        "name": ".CRT",
        "virtual_address": "0x9000",
        "virtual_size": 24,
        "raw_size": 512,
        "entropy": 0.1145,
        "characteristics": "0xc0300040",
        "is_executable": false,
        "is_writable": true,
        "is_readable": true
      },
      {
        "name": ".tls",
        "virtual_address": "0xa000",
        "virtual_size": 32,
        "raw_size": 512,
        "entropy": 0.2248,
        "characteristics": "0xc0300040",
        "is_executable": false,
        "is_writable": true,
        "is_readable": true
      },
      {
        "name": "/14",
        "virtual_address": "0xb000",
        "virtual_size": 56,
        "raw_size": 512,
        "entropy": 0.2162,
        "characteristics": "0x42400040",
        "is_executable": false,
        "is_writable": false,
        "is_readable": true
      },
      {
        "name": "/29",
        "virtual_address": "0xc000",
        "virtual_size": 7423,
        "raw_size": 7680,
        "entropy": 5.7665,
        "characteristics": "0x42100040",
        "is_executable": false,
        "is_writable": false,
        "is_readable": true
      },
      {
        "name": "/41",
        "virtual_address": "0xe000",
        "virtual_size": 303,
        "raw_size": 512,
        "entropy": 3.0441,
        "characteristics": "0x42100040",
        "is_executable": false,
        "is_writable": false,
        "is_readable": true
      },
      {
        "name": "/55",
        "virtual_address": "0xf000",
        "virtual_size": 456,
        "raw_size": 512,
        "entropy": 4.3174,
        "characteristics": "0x42100040",
        "is_executable": false,
        "is_writable": false,
        "is_readable": true
      },
      {
        "name": "/67",
        "virtual_address": "0x10000",
        "virtual_size": 56,
        "raw_size": 512,
        "entropy": 0.6707,
        "characteristics": "0x42300040",
        "is_executable": false,
        "is_writable": false,
        "is_readable": true
      }
    ],
    "imports": {
      "kernel32.dll": [
        "DeleteCriticalSection",
        "EnterCriticalSection",
        "ExitProcess",
        "FindClose",
        "FindFirstFileA",
        "FindNextFileA",
        "FreeLibrary",
        "GetCommandLineA",
        "GetLastError",
        "GetModuleHandleA",
        "GetProcAddress",
        "InitializeCriticalSection",
        "LeaveCriticalSection",
        "LoadLibraryA",
        "SetUnhandledExceptionFilter",
        "TlsGetValue",
        "VirtualProtect",
        "VirtualQuery"
      ],
      "msvcrt.dll": [
        "__getmainargs",
        "__mb_cur_max",
        "__p__environ",
        "__p__fmode",
        "__set_app_type",
        "_cexit",
        "_errno",
        "_fpreset",
        "_fullpath",
        "_iob",
        "_isctype",
        "_onexit",
        "_pctype",
        "_setmode",
        "abort",
        "atexit",
        "calloc",
        "free",
        "fwrite",
        "malloc",
        "mbstowcs",
        "memcpy",
        "printf",
        "puts",
        "realloc",
        "setlocale",
        "signal",
        "strcoll",
        "strlen",
        "tolower",
        "vfprintf",
        "wcstombs"
      ]
    },
    "exports": [],
    "resources": [],
    "dangerous_imports": [
      {
        "dll": "kernel32.dll",
        "function": "VirtualProtect"
      }
    ],
    "suspicious_import_count": 1,
    "total_import_count": 52,
    "has_debug_info": false,
    "is_packed": false,
    "packer_indicators": [],
    "overall_entropy": 2.6625
  },
  "lief_analysis": {
    "format": "PE",
    "is_pie": false,
    "has_nx": false,
    "has_stack_canary": false,
    "tls_callbacks": [
      "0x401ae0",
      "0x401a90"
    ],
    "relocations_count": 0,
    "signatures": [],
    "overlay_size": 132178,
    "overlay_entropy": 7.8914,
    "has_authenticode": false,
    "authenticode_valid": false,
    "tls_warning": "TLS callbacks detected \u2014 possible anti-debug",
    "overlay_warning": "High-entropy overlay \u2014 may contain encrypted payload"
  },
  "zip_analysis": {},
  "string_analysis": {
    "total_strings": 1419,
    "suspicious_hits": [
      {
        "pattern": "Run",
        "context": "!This program cannot be run in DOS mode."
      },
      {
        "pattern": ".dll",
        "context": "libgcc_s_dw2-1.dll"
      },
      {
        "pattern": "VirtualAlloc",
        "context": "VirtualAllocEx"
      },
      {
        "pattern": "VirtualAllocEx",
        "context": "VirtualAllocEx"
      },
      {
        "pattern": "WriteProcessMemory",
        "context": "WriteProcessMemory"
      },
      {
        "pattern": "CreateRemoteThread",
        "context": "CreateRemoteThread"
      },
      {
        "pattern": "CryptEncrypt",
        "context": "CryptEncrypt"
      },
      {
        "pattern": "encrypt",
        "context": "CryptEncrypt"
      },
      {
        "pattern": "Startup",
        "context": "_mainCRTStartup"
      }
    ],
    "urls_found": [],
    "ips_found": [],
    "sample_strings": [
      "!This program cannot be run in DOS mode.",
      ".text",
      "P`.data",
      ".rdata",
      "0@.bss",
      ".idata",
      "@B/29",
      "L[^_]",
      "L[^_]",
      "<]ta<",
      "<]t.<",
      ",[^_]",
      ",[^_]",
      "t(<{t?",
      "D\f\u000b</t&<\\t\"",
      "libgcc_s_dw2-1.dll",
      "__register_frame_info",
      "__deregister_frame_info",
      "libgcj-16.dll",
      "_Jv_RegisterClasses",
      "StealthOS Suspicious Test Binary",
      "kernel32.dll",
      "VirtualAllocEx",
      "WriteProcessMemory",
      "CreateRemoteThread",
      "advapi32.dll",
      "CryptEncrypt",
      "Resolved pointers: %p, %p, %p, %p",
      "Mingw runtime failure:",
      "  VirtualQuery failed for %d bytes at address %p",
      "  Unknown pseudo relocation protocol version %d.",
      "  Unknown pseudo relocation bit size %d.",
      "glob-1.0-mingw32",
      "GCC: (GNU) 6.3.0",
      "GCC: (GNU) 6.3.0",
      "GCC: (MinGW.org GCC-6.3.0-1) 6.3.0",
      "GCC: (GNU) 6.3.0",
      "GCC: (GNU) 6.3.0",
      "GCC: (GNU) 6.3.0",
      "GCC: (GNU) 6.3.0",
      "GCC: (GNU) 6.3.0",
      "GCC: (GNU) 6.3.0",
      "GCC: (GNU) 6.3.0",
      "GCC: (GNU) 6.3.0",
      "GCC: (GNU) 6.3.0",
      "GCC: (GNU) 6.3.0",
      "GCC: (GNU) 6.3.0",
      "GCC: (GNU) 6.3.0",
      "GCC: (GNU) 6.3.0",
      "GCC: (GNU) 6.3.0",
      "GCC: (GNU) 6.3.0",
      "GCC: (GNU) 6.3.0",
      "GCC: (GNU) 6.3.0",
      "DeleteCriticalSection",
      "EnterCriticalSection",
      "ExitProcess",
      "FindClose",
      "FindFirstFileA",
      "FindNextFileA",
      "FreeLibrary",
      "GetCommandLineA",
      "GetLastError",
      "GetModuleHandleA",
      "GetProcAddress",
      "InitializeCriticalSection",
      "LeaveCriticalSection",
      "LoadLibraryA",
      "SetUnhandledExceptionFilter",
      "TlsGetValue",
      "VirtualProtect",
      "VirtualQuery",
      "_strdup",
      "_stricoll",
      "__getmainargs",
      "__mb_cur_max",
      "__p__environ",
      "__p__fmode",
      "__set_app_type",
      "_cexit",
      "_errno",
      "_fpreset",
      "_fullpath",
      "_isctype",
      "_onexit",
      "_pctype",
      "_setmode",
      "abort",
      "atexit",
      "calloc",
      "fwrite",
      "malloc",
      "mbstowcs",
      "memcpy",
      "printf",
      "realloc",
      "setlocale",
      "signal",
      "strcoll",
      "strlen",
      "tolower",
      "vfprintf",
      "wcstombs",
      "KERNEL32.dll",
      "msvcrt.dll",
      "msvcrt.dll",
      "../../../src/gcc-6.3.0/libgcc/config/i386/cygwin.S",
      "/home/keith/src/mingw/gcc-build/gcc-6.3.0-mingw32-cross-native/mingw32/libgcc",
      "GNU AS 2.28",
      "GNU C11 6.3.0 -mtune=generic -march=i586 -g -g -g -O2 -O2 -O2 -fbuilding-libgcc -fno-stack-protector",
      "\f../../../src/gcc-6.3.0/libgcc/libgcc2.c",
      "/home/keith/src/mingw/gcc-build/gcc-6.3.0-mingw32-cross-native/mingw32/libgcc",
      "unsigned int",
      "short unsigned int",
      "long long int",
      "long double",
      "long int",
      "_iobuf",
      "_base",
      "_flag",
      "_file",
      "_charbuf",
      "_bufsiz",
      "_tmpfname",
      "short int",
      "long unsigned int",
      "_argc",
      "_argv",
      "__mb_cur_max",
      "_sys_nerr",
      "_sys_errlist",
      "_osver",
      "_winver",
      "_winmajor",
      "_winminor",
      "\u000b_fmode",
      "sizetype",
      "optind",
      "optopt",
      "opterr",
      "optarg",
      "\u000b_daylight",
      "\u000b_timezone",
      "\u000b_tzname",
      "\u000bdaylight",
      "\u000btimezone",
      "\u000btzname",
      "hashval_t",
      "htab_hash",
      "htab_eq",
      "htab_hash_pointer",
      "htab_eq_pointer",
      "unsigned char",
      "stringop_alg",
      "no_stringop",
      "libcall",
      "rep_prefix_1_byte",
      "rep_prefix_4_byte",
      "rep_prefix_8_byte",
      "loop_1_byte",
      "unrolled_loop",
      "vector_loop",
      "last_alg",
      "\u000bunspec_strings",
      "\u000bunspecv_strings",
      "stringop_strategy",
      "noalign",
      "stringop_algs",
      "unknown_size",
      "processor_costs",
      "shift_var",
      "shift_const",
      "mult_init",
      "mult_bit",
      "divide",
      "movsx",
      "movzx",
      "large_insn",
      "move_ratio",
      "movzbl_load",
      "int_load",
      "int_store",
      "fp_move",
      "fp_load",
      "fp_store",
      "mmx_move",
      "mmx_load",
      "mmx_store",
      "sse_move",
      "sse_load",
      "sse_store",
      "mmxsse_to_integer",
      "l1_cache_size",
      "l2_cache_size",
      "prefetch_block",
      "simultaneous_prefetches",
      "branch_cost",
      "fsqrt",
      "memcpy",
      "memset",
      "scalar_stmt_cost"
    ]
  },
  "heuristic_risk": {
    "score": 35,
    "risk_level": "LOW",
    "reasons": [
      "TLS callbacks detected \u2014 anti-debug technique (+10)",
      "High-entropy data overlay \u2014 hidden payload (+12)",
      "9 suspicious string patterns (+8)",
      "Unsigned executable (+5)"
    ]
  }
}